README.md
TODO
setup.py
examples/demo.py
examples/wsgi-demo.py
pooledProcessMixin/__init__.py
pooled_ProcessMixIn.egg-info/PKG-INFO
pooled_ProcessMixIn.egg-info/SOURCES.txt
pooled_ProcessMixIn.egg-info/dependency_links.txt
pooled_ProcessMixIn.egg-info/top_level.txt